{
    "add_subplot": false, 
    "ana_modules": [
        "Efficiency", 
        "TriggerEfficiencyFit"
    ], 
    "argv": "./plotter.py -i _emul:~/dust/dijetana/ana/CMSSW_7_2_3/TRIGGER_PTAVG_DATA.root?yb1ys0/TriggerEffs/emul_HLT_PFJET320 _trg:~/dust/dijetana/ana/CMSSW_7_2_3/TRIGGER_PTAVG_DATA.root?yb1ys0/TriggerEffs/HLT_PFJET260 --label _emul:emul _trg:trg --ana-modules Efficiency TriggerEfficiencyFit --efficiency _emul:_trg --y-lim 0.0 1.1 --color eff_emul:black --x-label _ptavg_ --y-label Efficiency --label eff_emul:HLT_PFJet_320 --output-path trigger_eff_hltpfjet320.png --trigger-efficiency-fit eff_emul:{} --style fit_eff_emul:line --ax-texts _cmsp_ _20fb_", 
    "ax_hlines": [], 
    "ax_texts": [
        "_cmsp_", 
        "_20fb_"
    ], 
    "ax_vlines": [], 
    "combine_legend_entries": [], 
    "efficiency": [
        [
            "_emul", 
            "_trg"
        ]
    ], 
    "fig_size": null, 
    "input_modules": [
        "RootModule"
    ], 
    "legend_loc": "best", 
    "list_modules": false, 
    "load_config": [
        "plots/trigger_eff_hltpfjet320_yb1ys0.json"
    ], 
    "log_level": "info", 
    "objects": {
        "_default": {
            "alpha": 1.0, 
            "axis": "ax", 
            "capsize": 0, 
            "cmap": "viridis", 
            "color": "auto", 
            "edgecolor": "auto", 
            "label": "__nolegend__", 
            "linestyle": "", 
            "marker": ".", 
            "step": false, 
            "style": "errorbar", 
            "x_err": true, 
            "y_err": true, 
            "zorder": 1.0
        }, 
        "_emul": {
            "input": "~/dust/dijetana/ana/CMSSW_7_2_3/TRIGGER_PTAVG_DATA.root?yb1ys0/TriggerEffs/emul_HLT_PFJET320", 
            "label": "emul"
        }, 
        "_trg": {
            "input": "~/dust/dijetana/ana/CMSSW_7_2_3/TRIGGER_PTAVG_DATA.root?yb1ys0/TriggerEffs/HLT_PFJET260", 
            "label": "trg"
        }, 
        "eff_emul": {
            "color": "black", 
            "label": "HLT_PFJet_320"
        }, 
        "fit_eff_emul": {
            "style": "line"
        }
    }, 
    "output_modules": [
        "PlotModule", 
        "CopyToWebModule"
    ], 
    "output_path": "trigger_eff_hltpfjet320_yb1ys0.png", 
    "output_prefix": "plots/", 
    "plot_id": "^(?!_).*", 
    "print_config": false, 
    "provided_args": [
        "ana_modules", 
        "input", 
        "efficiency", 
        "trigger_efficiency_fit", 
        "label", 
        "color", 
        "style", 
        "output_path", 
        "x_label", 
        "y_label", 
        "ax_texts"
    ], 
    "show_legend": true, 
    "trigger_efficiency_fit": [
        [
            "eff_emul", 
            {}
        ]
    ], 
    "x_label": "_ptavg_", 
    "x_lims": [
        null, 
        null
    ], 
    "x_log": false, 
    "y_label": "Efficiency", 
    "y_lims": [
        "0.0", 
        "1.1"
    ], 
    "y_log": false, 
    "y_subplot_label": "", 
    "y_subplot_lims": [
        null, 
        null
    ], 
    "z_label": "", 
    "z_lims": [
        null, 
        null
    ], 
    "z_log": false
}